_bmnsqlite3.cp37-win_amd64.pyd
bmnsqlite3/__init__.py
bmnsqlite3/dbapi2.py
bmnsqlite3/dump.py
bmnsqlite3/vfs.py
bmnsqlite3-0.1.0.dist-info/LICENSE
bmnsqlite3-0.1.0.dist-info/METADATA
bmnsqlite3-0.1.0.dist-info/WHEEL
bmnsqlite3-0.1.0.dist-info/top_level.txt
bmnsqlite3-0.1.0.dist-info/RECORD
