Metadata-Version: 2.1
Name: bmnsqlite3
Version: 0.1.0
Summary: SQLite3 Wrapper with VFS support
Home-page: https://github.com/BitMarketNetwork/bmnsqlite3/
Download-URL: https://github.com/BitMarketNetwork/bmnsqlite3/releases
Author: BitMarket Network
Author-email: support@bitmarket.network
License: GNU General Public License v3 (GPLv3)
Project-URL: Documentation, https://github.com/BitMarketNetwork/bmnsqlite3
Project-URL: Source, https://github.com/BitMarketNetwork/bmnsqlite3
Project-URL: Issues, https://github.com/BitMarketNetwork/bmnsqlite3/issues
Project-URL: Changelog, https://github.com/BitMarketNetwork/bmnsqlite3/blob/main/CHANGELOG.md
Keywords: bmnsqlite3,sqlite3,database
Platform: win32
Platform: darwin
Platform: linux
Classifier: Development Status :: 3 - Alpha
Classifier: Intended Audience :: Developers
Classifier: License :: OSI Approved :: GNU General Public License v3 (GPLv3)
Classifier: Natural Language :: English
Classifier: Operating System :: MacOS :: MacOS X
Classifier: Operating System :: Microsoft :: Windows
Classifier: Operating System :: POSIX :: Linux
Classifier: Programming Language :: C
Classifier: Programming Language :: Python :: 3 :: Only
Classifier: Topic :: Database :: Front-Ends
Classifier: Topic :: Software Development :: Libraries :: Python Modules
Classifier: Topic :: Utilities
Requires-Python: <3.11,>=3.7
License-File: LICENSE
Provides-Extra: dev
Requires-Dist: setuptools (>=51.0.0) ; extra == 'dev'
Requires-Dist: wheel (>=0.36) ; extra == 'dev'
Requires-Dist: build (>=0.7) ; extra == 'dev'
Requires-Dist: twine (>=3.4) ; extra == 'dev'
Requires-Dist: tox (>=3.23) ; extra == 'dev'
Requires-Dist: cryptography (>=3.4.7) ; extra == 'dev'
